streamlit_theta/__init__.py
streamlit_theta/editor/__init__.py
streamlit_theta/editor/audio.py
streamlit_theta/editor/chart.py
streamlit_theta/editor/csv.py
streamlit_theta/editor/diagram.py
streamlit_theta/editor/document.py
streamlit_theta/editor/form.py
streamlit_theta/editor/image.py
streamlit_theta/editor/mindmap.py
streamlit_theta/editor/newsletter.py
streamlit_theta/editor/slide.py
streamlit_theta/editor/spreadsheet.py
streamlit_theta/editor/video.py
streamlit_theta-1.0.2.dist-info/licenses/LICENSE
streamlit_theta-1.0.2.dist-info/METADATA
streamlit_theta-1.0.2.dist-info/WHEEL
streamlit_theta-1.0.2.dist-info/top_level.txt
streamlit_theta-1.0.2.dist-info/RECORD
