Metadata-Version: 2.4
Name: streamlit-theta
Version: 1.0.2
Summary: Comprehensive visual editors suite for Streamlit: presentations, documents, spreadsheets, charts, images, forms, mind maps, diagrams, newsletters, and more. Professional-grade editing tools for modern web applications.
Home-page: https://github.com/arcana/streamlit-theta
Author: CelsiaSolaraStarflare
Author-email: CelsiaSolaraStarflare <celsiastarflare@outlook.com>
License: Apache-2.0
Project-URL: Homepage, https://github.com/CelsiaSolaraStarflare/streamlit-theta
Project-URL: Bug Reports, https://github.com/CelsiaSolaraStarflare/streamlit-theta/issues
Project-URL: Source, https://github.com/CelsiaSolaraStarflare/streamlit-theta
Keywords: streamlit,editor,visual,presentation,document,spreadsheet,chart,image,form,mindmap,diagram,newsletter,drag-drop,wysiwyg,open-source
Classifier: Development Status :: 4 - Beta
Classifier: Intended Audience :: Developers
Classifier: License :: OSI Approved :: Apache Software License
Classifier: Operating System :: OS Independent
Classifier: Programming Language :: Python :: 3
Classifier: Programming Language :: Python :: 3.7
Classifier: Programming Language :: Python :: 3.8
Classifier: Programming Language :: Python :: 3.9
Classifier: Programming Language :: Python :: 3.10
Classifier: Programming Language :: Python :: 3.11
Classifier: Programming Language :: Python :: 3.12
Classifier: Programming Language :: Python :: 3.13
Classifier: Topic :: Software Development :: Libraries :: Python Modules
Classifier: Topic :: Office/Business :: Financial :: Spreadsheet
Classifier: Topic :: Multimedia :: Graphics :: Presentation
Requires-Python: >=3.7
License-File: LICENSE
Requires-Dist: streamlit>=1.0.0
Dynamic: author
Dynamic: home-page
Dynamic: license-file
Dynamic: requires-python
